mul/venkat/singleCycleProcessor/multi_1/rtl/multi_12.v
module booth_radix4_multiplier (
    input  signed [3:0] A,   // multiplicand
    input  signed [3:0] B,   // multiplier
    output signed [7:0] P    // final product
);
    reg signed [7:0] pp0, pp1;  
    reg signed [7:0] result;
    reg [4:0] B_ext;          // <---- Moved here, not inside always

    always @(*) begin
        B_ext = {B, 1'b0};  

        // ---- Group 0 ----
        case (B_ext[2:0])
            3'b000, 3'b111: pp0 = 8'd0;
            3'b001, 3'b010: pp0 = {{4{A[3]}}, A};
            3'b011:         pp0 = {{3{A[3]}}, A, 1'b0};
            3'b100:         pp0 = -{{3{A[3]}}, A, 1'b0};
            3'b101, 3'b110: pp0 = -{{4{A[3]}}, A};
        endcase

        // ---- Group 1 ----
        case (B_ext[4:2])
            3'b000, 3'b111: pp1 = 8'd0;
            3'b001, 3'b010: pp1 = {{4{A[3]}}, A} << 2;
            3'b011:         pp1 = ({{3{A[3]}}, A, 1'b0}) << 2;
            3'b100:         pp1 = -( {{3{A[3]}}, A, 1'b0} << 2);
            3'b101, 3'b110: pp1 = -( {{4{A[3]}}, A} << 2);
        endcase

        result = pp0 + pp1;
    end

    assign P = result;
endmodule

mul/venkat/singleCycleProcessor/multi_1/multi_12_tb.v
// tb_booth_radix4_multiplier.v
`timescale 1ns/1ps
module tb_booth_radix4_multiplier;

    reg signed [3:0] A, B;   // inputs
    wire signed [7:0] P;     // DUT output
    reg signed [7:0] expected;

    integer i, j;

    // Instantiate DUT
    booth_radix4_multiplier dut (
        .A(A),
        .B(B),
        .P(P)
    );

    initial begin
        $dumpfile("booth_mult.vcd");
        $dumpvars(0, tb_booth_radix4_multiplier);

        $shm_open("wave.shm");
        $shm_probe("ACTMF");

        $display("Testing Booth Radix-4 Multiplier...");

        // Loop through some test cases
        for (i = -8; i <= 7; i = i + 1) begin
            for (j = -8; j <= 7; j = j + 1) begin
                A = i;
                B = j;
                expected = A * B;
                #5; // wait for DUT to compute

                if (P !== expected) begin
                    $display("FAIL: A=%0d, B=%0d | DUT=%0d, Expected=%0d", 
                             A, B, P, expected);
                end else begin
                    $display("PASS: A=%0d, B=%0d | Product=%0d", 
                             A, B, P);
                end
            end
        end

        $finish;
    end
endmodule

mul/venkat/singleCycleProcessor/multi_1/booth_mult.vcd
$date
    Feb 18, 2019  06:47:11
$end
$version
    TOOL:	ncsim(64)	15.20-s051
$end
$timescale
    1 ps
$end

$scope module tb_booth_radix4_multiplier $end
$var reg       4 !    A [3:0] $end
$var reg       4 "    B [3:0] $end
$var wire      8 #    P [7:0] $end
$var reg       8 $    expected [7:0] $end
$var integer  32 %    i  $end
$var integer  32 &    j  $end

$scope module dut $end
$var wire      4 '    A [3:0] $end
$var wire      4 (    B [3:0] $end
$var wire      8 #    P [7:0] $end
$var reg       8 )    pp0 [7:0] $end
$var reg       8 *    pp1 [7:0] $end
$var reg       8 +    result [7:0] $end
$var reg       5 ,    B_ext [4:0] $end
$upscope $end

$upscope $end

$enddefinitions $end
$dumpvars
b1000 !
b1000 "
b1000000 #
b1000000 $
b11111111111111111111111111111000 %
b11111111111111111111111111111000 &
b1000 '
b1000 (
b0 )
b1000000 *
b1000000 +
b10000 ,
$end
#5000
b11111111111111111111111111111001 &
b1001 "
b111000 $
b1001 (
b10010 ,
b11111000 )
b111000 +
b111000 #
#10000
b11111111111111111111111111111010 &
b1010 "
b110000 $
b1010 (
b10100 ,
b10000 )
b100000 *
b110000 +
b110000 #
#15000
b11111111111111111111111111111011 &
b1011 "
b101000 $
b1011 (
b10110 ,
b1000 )
b101000 +
b101000 #
#20000
b11111111111111111111111111111100 &
b1100 "
b100000 $
b1100 (
b11000 ,
b0 )
b100000 +
b100000 #
#25000
b11111111111111111111111111111101 &
b1101 "
b11000 $
b1101 (
b11010 ,
b11111000 )
b11000 +
b11000 #
#30000
b11111111111111111111111111111110 &
b1110 "
b10000 $
b1110 (
b11100 ,
b10000 )
b0 *
b10000 +
b10000 #
#35000
b11111111111111111111111111111111 &
b1111 "
b1000 $
b1111 (
b11110 ,
b1000 )
b1000 +
b1000 #
#40000
b0 &
b0 "
b0 $
b0 (
b0 ,
b0 )
b0 +
b0 #
#45000
b1 &
b1 "
b11111000 $
b1 (
b10 ,
b11111000 )
b11111000 +
b11111000 #
#50000
b10 &
b10 "
b11110000 $
b10 (
b100 ,
b10000 )
b11100000 *
b11110000 +
b11110000 #
#55000
b11 &
b11 "
b11101000 $
b11 (
b110 ,
b1000 )
b11101000 +
b11101000 #
#60000
b100 &
b100 "
b11100000 $
b100 (
b1000 ,
b0 )
b11100000 +
b11100000 #
#65000
b101 &
b101 "
b11011000 $
b101 (
b1010 ,
b11111000 )
b11011000 +
b11011000 #
#70000
b110 &
b110 "
b11010000 $
b110 (
b1100 ,
b10000 )
b11000000 *
b11010000 +
b11010000 #
#75000
b111 &
b111 "
b11001000 $
b111 (
b1110 ,
b1000 )
b11001000 +
b11001000 #
#80000
b1000 &
b11111111111111111111111111111001 %
b11111111111111111111111111111000 &
b1001 !
b1000 "
b111000 $
b1000 (
b1001 '
b10000 ,
b0 )
b111000 *
b111000 +
b111000 #
#85000
b11111111111111111111111111111001 &
b1001 "
b110001 $
b1001 (
b10010 ,
b11111001 )
b110001 +
b110001 #
#90000
b11111111111111111111111111111010 &
b1010 "
b101010 $
b1010 (
b10100 ,
b1110 )
b11100 *
b101010 +
b101010 #
#95000
b11111111111111111111111111111011 &
b1011 "
b100011 $
b1011 (
b10110 ,
b111 )
b100011 +
b100011 #
#100000
b11111111111111111111111111111100 &
b1100 "
b11100 $
b1100 (
b11000 ,
b0 )
b11100 +
b11100 #
#105000
b11111111111111111111111111111101 &
b1101 "
b10101 $
b1101 (
b11010 ,
b11111001 )
b10101 +
b10101 #
#110000
b11111111111111111111111111111110 &
b1110 "
b1110 $
b1110 (
b11100 ,
b1110 )
b0 *
b1110 +
b1110 #
#115000
b11111111111111111111111111111111 &
b1111 "
b111 $
b1111 (
b11110 ,
b111 )
b111 +
b111 #
#120000
b0 &
b0 "
b0 $
b0 (
b0 ,
b0 )
b0 +
b0 #
#125000
b1 &
b1 "
b11111001 $
b1 (
b10 ,
b11111001 )
b11111001 +
b11111001 #
#130000
b10 &
b10 "
b11110010 $
b10 (
b100 ,
b1110 )
b11100100 *
b11110010 +
b11110010 #
#135000
b11 &
b11 "
b11101011 $
b11 (
b110 ,
b111 )
b11101011 +
b11101011 #
#140000
b100 &
b100 "
b11100100 $
b100 (
b1000 ,
b0 )
b11100100 +
b11100100 #
#145000
b101 &
b101 "
b11011101 $
b101 (
b1010 ,
b11111001 )
b11011101 +
b11011101 #
#150000
b110 &
b110 "
b11010110 $
b110 (
b1100 ,
b1110 )
b11001000 *
b11010110 +
b11010110 #
#155000
b111 &
b111 "
b11001111 $
b111 (
b1110 ,
b111 )
b11001111 +
b11001111 #
#160000
b1000 &
b11111111111111111111111111111010 %
b11111111111111111111111111111000 &
b1010 !
b1000 "
b110000 $
b1000 (
b1010 '
b10000 ,
b0 )
b110000 *
b110000 +
b110000 #
#165000
b11111111111111111111111111111001 &
b1001 "
b101010 $
b1001 (
b10010 ,
b11111010 )
b101010 +
b101010 #
#170000
b11111111111111111111111111111010 &
b1010 "
b100100 $
b1010 (
b10100 ,
b1100 )
b11000 *
b100100 +
b100100 #
#175000
b11111111111111111111111111111011 &
b1011 "
b11110 $
b1011 (
b10110 ,
b110 )
b11110 +
b11110 #
#180000
b11111111111111111111111111111100 &
b1100 "
b11000 $
b1100 (
b11000 ,
b0 )
b11000 +
b11000 #
#185000
b11111111111111111111111111111101 &
b1101 "
b10010 $
b1101 (
b11010 ,
b11111010 )
b10010 +
b10010 #
#190000
b11111111111111111111111111111110 &
b1110 "
b1100 $
b1110 (
b11100 ,
b1100 )
b0 *
b1100 +
b1100 #
#195000
b11111111111111111111111111111111 &
b1111 "
b110 $
b1111 (
b11110 ,
b110 )
b110 +
b110 #
#200000
b0 &
b0 "
b0 $
b0 (
b0 ,
b0 )
b0 +
b0 #
#205000
b1 &
b1 "
b11111010 $
b1 (
b10 ,
b11111010 )
b11111010 +
b11111010 #
#210000
b10 &
b10 "
b11110100 $
b10 (
b100 ,
b1100 )
b11101000 *
b11110100 +
b11110100 #
#215000
b11 &
b11 "
b11101110 $
b11 (
b110 ,
b110 )
b11101110 +
b11101110 #
#220000
b100 &
b100 "
b11101000 $
b100 (
b1000 ,
b0 )
b11101000 +
b11101000 #
#225000
b101 &
b101 "
b11100010 $
b101 (
b1010 ,
b11111010 )
b11100010 +
b11100010 #
#230000
b110 &
b110 "
b11011100 $
b110 (
b1100 ,
b1100 )
b11010000 *
b11011100 +
b11011100 #
#235000
b111 &
b111 "
b11010110 $
b111 (
b1110 ,
b110 )
b11010110 +
b11010110 #
#240000
b1000 &
b11111111111111111111111111111011 %
b11111111111111111111111111111000 &
b1011 !
b1000 "
b101000 $
b1000 (
b1011 '
b10000 ,
b0 )
b101000 *
b101000 +
b101000 #
#245000
b11111111111111111111111111111001 &
b1001 "
b100011 $
b1001 (
b10010 ,
b11111011 )
b100011 +
b100011 #
#250000
b11111111111111111111111111111010 &
b1010 "
b11110 $
b1010 (
b10100 ,
b1010 )
b10100 *
b11110 +
b11110 #
#255000
b11111111111111111111111111111011 &
b1011 "
b11001 $
b1011 (
b10110 ,
b101 )
b11001 +
b11001 #
#260000
b11111111111111111111111111111100 &
b1100 "
b10100 $
b1100 (
b11000 ,
b0 )
b10100 +
b10100 #
#265000
b11111111111111111111111111111101 &
b1101 "
b1111 $
b1101 (
b11010 ,
b11111011 )
b1111 +
b1111 #
#270000
b11111111111111111111111111111110 &
b1110 "
b1010 $
b1110 (
b11100 ,
b1010 )
b0 *
b1010 +
b1010 #
#275000
b11111111111111111111111111111111 &
b1111 "
b101 $
b1111 (
b11110 ,
b101 )
b101 +
b101 #
#280000
b0 &
b0 "
b0 $
b0 (
b0 ,
b0 )
b0 +
b0 #
#285000
b1 &
b1 "
b11111011 $
b1 (
b10 ,
b11111011 )
b11111011 +
b11111011 #
#290000
b10 &
b10 "
b11110110 $
b10 (
b100 ,
b1010 )
b11101100 *
b11110110 +
b11110110 #
#295000
b11 &
b11 "
b11110001 $
b11 (
b110 ,
b101 )
b11110001 +
b11110001 #
#300000
b100 &
b100 "
b11101100 $
b100 (
b1000 ,
b0 )
b11101100 +
b11101100 #
#305000
b101 &
b101 "
b11100111 $
b101 (
b1010 ,
b11111011 )
b11100111 +
b11100111 #
#310000
b110 &
b110 "
b11100010 $
b110 (
b1100 ,
b1010 )
b11011000 *
b11100010 +
b11100010 #
#315000
b111 &
b111 "
b11011101 $
b111 (
b1110 ,
b101 )
b11011101 +
b11011101 #
#320000
b1000 &
b11111111111111111111111111111100 %
b11111111111111111111111111111000 &
b1100 !
b1000 "
b100000 $
b1000 (
b1100 '
b10000 ,
b0 )
b100000 *
b100000 +
b100000 #
#325000
b11111111111111111111111111111001 &
b1001 "
b11100 $
b1001 (
b10010 ,
b11111100 )
b11100 +
b11100 #
#330000
b11111111111111111111111111111010 &
b1010 "
b11000 $
b1010 (
b10100 ,
b1000 )
b10000 *
b11000 +
b11000 #
#335000
b11111111111111111111111111111011 &
b1011 "
b10100 $
b1011 (
b10110 ,
b100 )
b10100 +
b10100 #
#340000
b11111111111111111111111111111100 &
b1100 "
b10000 $
b1100 (
b11000 ,
b0 )
b10000 +
b10000 #
#345000
b11111111111111111111111111111101 &
b1101 "
b1100 $
b1101 (
b11010 ,
b11111100 )
b1100 +
b1100 #
#350000
b11111111111111111111111111111110 &
b1110 "
b1000 $
b1110 (
b11100 ,
b1000 )
b0 *
b1000 +
b1000 #
#355000
b11111111111111111111111111111111 &
b1111 "
b100 $
b1111 (
b11110 ,
b100 )
b100 +
b100 #
#360000
b0 &
b0 "
b0 $
b0 (
b0 ,
b0 )
b0 +
b0 #
#365000
b1 &
b1 "
b11111100 $
b1 (
b10 ,
b11111100 )
b11111100 +
b11111100 #
#370000
b10 &
b10 "
b11111000 $
b10 (
b100 ,
b1000 )
b11110000 *
b11111000 +
b11111000 #
#375000
b11 &
b11 "
b11110100 $
b11 (
b110 ,
b100 )
b11110100 +
b11110100 #
#380000
b100 &
b100 "
b11110000 $
b100 (
b1000 ,
b0 )
b11110000 +
b11110000 #
#385000
b101 &
b101 "
b11101100 $
b101 (
b1010 ,
b11111100 )
b11101100 +
b11101100 #
#390000
b110 &
b110 "
b11101000 $
b110 (
b1100 ,
b1000 )
b11100000 *
b11101000 +
b11101000 #
#395000
b111 &
b111 "
b11100100 $
b111 (
b1110 ,
b100 )
b11100100 +
b11100100 #
#400000
b1000 &
b11111111111111111111111111111101 %
b11111111111111111111111111111000 &
b1101 !
b1000 "
b11000 $
b1000 (
b1101 '
b10000 ,
b0 )
b11000 *
b11000 +
b11000 #
#405000
b11111111111111111111111111111001 &
b1001 "
b10101 $
b1001 (
b10010 ,
b11111101 )
b10101 +
b10101 #
#410000
b11111111111111111111111111111010 &
b1010 "
b10010 $
b1010 (
b10100 ,
b110 )
b1100 *
b10010 +
b10010 #
#415000
b11111111111111111111111111111011 &
b1011 "
b1111 $
b1011 (
b10110 ,
b11 )
b1111 +
b1111 #
#420000
b11111111111111111111111111111100 &
b1100 "
b1100 $
b1100 (
b11000 ,
b0 )
b1100 +
b1100 #
#425000
b11111111111111111111111111111101 &
b1101 "
b1001 $
b1101 (
b11010 ,
b11111101 )
b1001 +
b1001 #
#430000
b11111111111111111111111111111110 &
b1110 "
b110 $
b1110 (
b11100 ,
b110 )
b0 *
b110 +
b110 #
#435000
b11111111111111111111111111111111 &
b1111 "
b11 $
b1111 (
b11110 ,
b11 )
b11 +
b11 #
#440000
b0 &
b0 "
b0 $
b0 (
b0 ,
b0 )
b0 +
b0 #
#445000
b1 &
b1 "
b11111101 $
b1 (
b10 ,
b11111101 )
b11111101 +
b11111101 #
#450000
b10 &
b10 "
b11111010 $
b10 (
b100 ,
b110 )
b11110100 *
b11111010 +
b11111010 #
#455000
b11 &
b11 "
b11110111 $
b11 (
b110 ,
b11 )
b11110111 +
b11110111 #
#460000
b100 &
b100 "
b11110100 $
b100 (
b1000 ,
b0 )
b11110100 +
b11110100 #
#465000
b101 &
b101 "
b11110001 $
b101 (
b1010 ,
b11111101 )
b11110001 +
b11110001 #
#470000
b110 &
b110 "
b11101110 $
b110 (
b1100 ,
b110 )
b11101000 *
b11101110 +
b11101110 #
#475000
b111 &
b111 "
b11101011 $
b111 (
b1110 ,
b11 )
b11101011 +
b11101011 #
#480000
b1000 &
b11111111111111111111111111111110 %
b11111111111111111111111111111000 &
b1110 !
b1000 "
b10000 $
b1000 (
b1110 '
b10000 ,
b0 )
b10000 *
b10000 +
b10000 #
#485000
b11111111111111111111111111111001 &
b1001 "
b1110 $
b1001 (
b10010 ,
b11111110 )
b1110 +
b1110 #
#490000
b11111111111111111111111111111010 &
b1010 "
b1100 $
b1010 (
b10100 ,
b100 )
b1000 *
b1100 +
b1100 #
#495000
b11111111111111111111111111111011 &
b1011 "
b1010 $
b1011 (
b10110 ,
b10 )
b1010 +
b1010 #
#500000
b11111111111111111111111111111100 &
b1100 "
b1000 $
b1100 (
b11000 ,
b0 )
b1000 +
b1000 #
#505000
b11111111111111111111111111111101 &
b1101 "
b110 $
b1101 (
b11010 ,
b11111110 )
b110 +
b110 #
#510000
b11111111111111111111111111111110 &
b1110 "
b100 $
b1110 (
b11100 ,
b100 )
b0 *
b100 +
b100 #
#515000
b11111111111111111111111111111111 &
b1111 "
b10 $
b1111 (
b11110 ,
b10 )
b10 +
b10 #
#520000
b0 &
b0 "
b0 $
b0 (
b0 ,
b0 )
b0 +
b0 #
#525000
b1 &
b1 "
b11111110 $
b1 (
b10 ,
b11111110 )
b11111110 +
b11111110 #
#530000
b10 &
b10 "
b11111100 $
b10 (
b100 ,
b100 )
b11111000 *
b11111100 +
b11111100 #
#535000
b11 &
b11 "
b11111010 $
b11 (
b110 ,
b10 )
b11111010 +
b11111010 #
#540000
b100 &
b100 "
b11111000 $
b100 (
b1000 ,
b0 )
b11111000 +
b11111000 #
#545000
b101 &
b101 "
b11110110 $
b101 (
b1010 ,
b11111110 )
b11110110 +
b11110110 #
#550000
b110 &
b110 "
b11110100 $
b110 (
b1100 ,
b100 )
b11110000 *
b11110100 +
b11110100 #
#555000
b111 &
b111 "
b11110010 $
b111 (
b1110 ,
b10 )
b11110010 +
b11110010 #
#560000
b1000 &
b11111111111111111111111111111111 %
b11111111111111111111111111111000 &
b1111 !
b1000 "
b1000 $
b1000 (
b1111 '
b10000 ,
b0 )
b1000 *
b1000 +
b1000 #
#565000
b11111111111111111111111111111001 &
b1001 "
b111 $
b1001 (
b10010 ,
b11111111 )
b111 +
b111 #
#570000
b11111111111111111111111111111010 &
b1010 "
b110 $
b1010 (
b10100 ,
b10 )
b100 *
b110 +
b110 #
#575000
b11111111111111111111111111111011 &
b1011 "
b101 $
b1011 (
b10110 ,
b1 )
b101 +
b101 #
#580000
b11111111111111111111111111111100 &
b1100 "
b100 $
b1100 (
b11000 ,
b0 )
b100 +
b100 #
#585000
b11111111111111111111111111111101 &
b1101 "
b11 $
b1101 (
b11010 ,
b11111111 )
b11 +
b11 #
#590000
b11111111111111111111111111111110 &
b1110 "
b10 $
b1110 (
b11100 ,
b10 )
b0 *
b10 +
b10 #
#595000
b11111111111111111111111111111111 &
b1111 "
b1 $
b1111 (
b11110 ,
b1 )
b1 +
b1 #
#600000
b0 &
b0 "
b0 $
b0 (
b0 ,
b0 )
b0 +
b0 #
#605000
b1 &
b1 "
b11111111 $
b1 (
b10 ,
b11111111 )
b11111111 +
b11111111 #
#610000
b10 &
b10 "
b11111110 $
b10 (
b100 ,
b10 )
b11111100 *
b11111110 +
b11111110 #
#615000
b11 &
b11 "
b11111101 $
b11 (
b110 ,
b1 )
b11111101 +
b11111101 #
#620000
b100 &
b100 "
b11111100 $
b100 (
b1000 ,
b0 )
b11111100 +
b11111100 #
#625000
b101 &
b101 "
b11111011 $
b101 (
b1010 ,
b11111111 )
b11111011 +
b11111011 #
#630000
b110 &
b110 "
b11111010 $
b110 (
b1100 ,
b10 )
b11111000 *
b11111010 +
b11111010 #
#635000
b111 &
b111 "
b11111001 $
b111 (
b1110 ,
b1 )
b11111001 +
b11111001 #
#640000
b1000 &
b0 %
b11111111111111111111111111111000 &
b0 !
b1000 "
b0 $
b1000 (
b0 '
b10000 ,
b0 )
b0 *
b0 +
b0 #
#645000
b11111111111111111111111111111001 &
b1001 "
b1001 (
b10010 ,
#650000
b11111111111111111111111111111010 &
b1010 "
b1010 (
b10100 ,
#655000
b11111111111111111111111111111011 &
b1011 "
b1011 (
b10110 ,
#660000
b11111111111111111111111111111100 &
b1100 "
b1100 (
b11000 ,
#665000
b11111111111111111111111111111101 &
b1101 "
b1101 (
b11010 ,
#670000
b11111111111111111111111111111110 &
b1110 "
b1110 (
b11100 ,
#675000
b11111111111111111111111111111111 &
b1111 "
b1111 (
b11110 ,
#680000
b0 &
b0 "
b0 (
b0 ,
#685000
b1 &
b1 "
b1 (
b10 ,
#690000
b10 &
b10 "
b10 (
b100 ,
#695000
b11 &
b11 "
b11 (
b110 ,
#700000
b100 &
b100 "
b100 (
b1000 ,
#705000
b101 &
b101 "
b101 (
b1010 ,
#710000
b110 &
b110 "
b110 (
b1100 ,
#715000
b111 &
b111 "
b111 (
b1110 ,
#720000
b1000 &
b1 %
b11111111111111111111111111111000 &
b1 !
b1000 "
b11111000 $
b1000 (
b1 '
b10000 ,
b11111000 *
b11111000 +
b11111000 #
#725000
b11111111111111111111111111111001 &
b1001 "
b11111001 $
b1001 (
b10010 ,
b1 )
b11111001 +
b11111001 #
#730000
b11111111111111111111111111111010 &
b1010 "
b11111010 $
b1010 (
b10100 ,
b11111110 )
b11111100 *
b11111010 +
b11111010 #
#735000
b11111111111111111111111111111011 &
b1011 "
b11111011 $
b1011 (
b10110 ,
b11111111 )
b11111011 +
b11111011 #
#740000
b11111111111111111111111111111100 &
b1100 "
b11111100 $
b1100 (
b11000 ,
b0 )
b11111100 +
b11111100 #
#745000
b11111111111111111111111111111101 &
b1101 "
b11111101 $
b1101 (
b11010 ,
b1 )
b11111101 +
b11111101 #
#750000
b11111111111111111111111111111110 &
b1110 "
b11111110 $
b1110 (
b11100 ,
b11111110 )
b0 *
b11111110 +
b11111110 #
#755000
b11111111111111111111111111111111 &
b1111 "
b11111111 $
b1111 (
b11110 ,
b11111111 )
b11111111 +
b11111111 #
#760000
b0 &
b0 "
b0 $
b0 (
b0 ,
b0 )
b0 +
b0 #
#765000
b1 &
b1 "
b1 $
b1 (
b10 ,
b1 )
b1 +
b1 #
#770000
b10 &
b10 "
b10 $
b10 (
b100 ,
b11111110 )
b100 *
b10 +
b10 #
#775000
b11 &
b11 "
b11 $
b11 (
b110 ,
b11111111 )
b11 +
b11 #
#780000
b100 &
b100 "
b100 $
b100 (
b1000 ,
b0 )
b100 +
b100 #
#785000
b101 &
b101 "
b101 $
b101 (
b1010 ,
b1 )
b101 +
b101 #
#790000
b110 &
b110 "
b110 $
b110 (
b1100 ,
b11111110 )
b1000 *
b110 +
b110 #
#795000
b111 &
b111 "
b111 $
b111 (
b1110 ,
b11111111 )
b111 +
b111 #
#800000
b1000 &
b10 %
b11111111111111111111111111111000 &
b10 !
b1000 "
b11110000 $
b1000 (
b10 '
b10000 ,
b0 )
b11110000 *
b11110000 +
b11110000 #
#805000
b11111111111111111111111111111001 &
b1001 "
b11110010 $
b1001 (
b10010 ,
b10 )
b11110010 +
b11110010 #
#810000
b11111111111111111111111111111010 &
b1010 "
b11110100 $
b1010 (
b10100 ,
b11111100 )
b11111000 *
b11110100 +
b11110100 #
#815000
b11111111111111111111111111111011 &
b1011 "
b11110110 $
b1011 (
b10110 ,
b11111110 )
b11110110 +
b11110110 #
#820000
b11111111111111111111111111111100 &
b1100 "
b11111000 $
b1100 (
b11000 ,
b0 )
b11111000 +
b11111000 #
#825000
b11111111111111111111111111111101 &
b1101 "
b11111010 $
b1101 (
b11010 ,
b10 )
b11111010 +
b11111010 #
#830000
b11111111111111111111111111111110 &
b1110 "
b11111100 $
b1110 (
b11100 ,
b11111100 )
b0 *
b11111100 +
b11111100 #
#835000
b11111111111111111111111111111111 &
b1111 "
b11111110 $
b1111 (
b11110 ,
b11111110 )
b11111110 +
b11111110 #
#840000
b0 &
b0 "
b0 $
b0 (
b0 ,
b0 )
b0 +
b0 #
#845000
b1 &
b1 "
b10 $
b1 (
b10 ,
b10 )
b10 +
b10 #
#850000
b10 &
b10 "
b100 $
b10 (
b100 ,
b11111100 )
b1000 *
b100 +
b100 #
#855000
b11 &
b11 "
b110 $
b11 (
b110 ,
b11111110 )
b110 +
b110 #
#860000
b100 &
b100 "
b1000 $
b100 (
b1000 ,
b0 )
b1000 +
b1000 #
#865000
b101 &
b101 "
b1010 $
b101 (
b1010 ,
b10 )
b1010 +
b1010 #
#870000
b110 &
b110 "
b1100 $
b110 (
b1100 ,
b11111100 )
b10000 *
b1100 +
b1100 #
#875000
b111 &
b111 "
b1110 $
b111 (
b1110 ,
b11111110 )
b1110 +
b1110 #
#880000
b1000 &
b11 %
b11111111111111111111111111111000 &
b11 !
b1000 "
b11101000 $
b1000 (
b11 '
b10000 ,
b0 )
b11101000 *
b11101000 +
b11101000 #
#885000
b11111111111111111111111111111001 &
b1001 "
b11101011 $
b1001 (
b10010 ,
b11 )
b11101011 +
b11101011 #
#890000
b11111111111111111111111111111010 &
b1010 "
b11101110 $
b1010 (
b10100 ,
b11111010 )
b11110100 *
b11101110 +
b11101110 #
#895000
b11111111111111111111111111111011 &
b1011 "
b11110001 $
b1011 (
b10110 ,
b11111101 )
b11110001 +
b11110001 #
#900000
b11111111111111111111111111111100 &
b1100 "
b11110100 $
b1100 (
b11000 ,
b0 )
b11110100 +
b11110100 #
#905000
b11111111111111111111111111111101 &
b1101 "
b11110111 $
b1101 (
b11010 ,
b11 )
b11110111 +
b11110111 #
#910000
b11111111111111111111111111111110 &
b1110 "
b11111010 $
b1110 (
b11100 ,
b11111010 )
b0 *
b11111010 +
b11111010 #
#915000
b11111111111111111111111111111111 &
b1111 "
b11111101 $
b1111 (
b11110 ,
b11111101 )
b11111101 +
b11111101 #
#920000
b0 &
b0 "
b0 $
b0 (
b0 ,
b0 )
b0 +
b0 #
#925000
b1 &
b1 "
b11 $
b1 (
b10 ,
b11 )
b11 +
b11 #
#930000
b10 &
b10 "
b110 $
b10 (
b100 ,
b11111010 )
b1100 *
b110 +
b110 #
#935000
b11 &
b11 "
b1001 $
b11 (
b110 ,
b11111101 )
b1001 +
b1001 #
#940000
b100 &
b100 "
b1100 $
b100 (
b1000 ,
b0 )
b1100 +
b1100 #
#945000
b101 &
b101 "
b1111 $
b101 (
b1010 ,
b11 )
b1111 +
b1111 #
#950000
b110 &
b110 "
b10010 $
b110 (
b1100 ,
b11111010 )
b11000 *
b10010 +
b10010 #
#955000
b111 &
b111 "
b10101 $
b111 (
b1110 ,
b11111101 )
b10101 +
b10101 #
#960000
b1000 &
b100 %
b11111111111111111111111111111000 &
b100 !
b1000 "
b11100000 $
b1000 (
b100 '
b10000 ,
b0 )
b11100000 *
b11100000 +
b11100000 #
#965000
b11111111111111111111111111111001 &
b1001 "
b11100100 $
b1001 (
b10010 ,
b100 )
b11100100 +
b11100100 #
#970000
b11111111111111111111111111111010 &
b1010 "
b11101000 $
b1010 (
b10100 ,
b11111000 )
b11110000 *
b11101000 +
b11101000 #
#975000
b11111111111111111111111111111011 &
b1011 "
b11101100 $
b1011 (
b10110 ,
b11111100 )
b11101100 +
b11101100 #
#980000
b11111111111111111111111111111100 &
b1100 "
b11110000 $
b1100 (
b11000 ,
b0 )
b11110000 +
b11110000 #
#985000
b11111111111111111111111111111101 &
b1101 "
b11110100 $
b1101 (
b11010 ,
b100 )
b11110100 +
b11110100 #
#990000
b11111111111111111111111111111110 &
b1110 "
b11111000 $
b1110 (
b11100 ,
b11111000 )
b0 *
b11111000 +
b11111000 #
#995000
b11111111111111111111111111111111 &
b1111 "
b11111100 $
b1111 (
b11110 ,
b11111100 )
b11111100 +
b11111100 #
#1000000
b0 &
b0 "
b0 $
b0 (
b0 ,
b0 )
b0 +
b0 #
#1005000
b1 &
b1 "
b100 $
b1 (
b10 ,
b100 )
b100 +
b100 #
#1010000
b10 &
b10 "
b1000 $
b10 (
b100 ,
b11111000 )
b10000 *
b1000 +
b1000 #
#1015000
b11 &
b11 "
b1100 $
b11 (
b110 ,
b11111100 )
b1100 +
b1100 #
#1020000
b100 &
b100 "
b10000 $
b100 (
b1000 ,
b0 )
b10000 +
b10000 #
#1025000
b101 &
b101 "
b10100 $
b101 (
b1010 ,
b100 )
b10100 +
b10100 #
#1030000
b110 &
b110 "
b11000 $
b110 (
b1100 ,
b11111000 )
b100000 *
b11000 +
b11000 #
#1035000
b111 &
b111 "
b11100 $
b111 (
b1110 ,
b11111100 )
b11100 +
b11100 #
#1040000
b1000 &
b101 %
b11111111111111111111111111111000 &
b101 !
b1000 "
b11011000 $
b1000 (
b101 '
b10000 ,
b0 )
b11011000 *
b11011000 +
b11011000 #
#1045000
b11111111111111111111111111111001 &
b1001 "
b11011101 $
b1001 (
b10010 ,
b101 )
b11011101 +
b11011101 #
#1050000
b11111111111111111111111111111010 &
b1010 "
b11100010 $
b1010 (
b10100 ,
b11110110 )
b11101100 *
b11100010 +
b11100010 #
#1055000
b11111111111111111111111111111011 &
b1011 "
b11100111 $
b1011 (
b10110 ,
b11111011 )
b11100111 +
b11100111 #
#1060000
b11111111111111111111111111111100 &
b1100 "
b11101100 $
b1100 (
b11000 ,
b0 )
b11101100 +
b11101100 #
#1065000
b11111111111111111111111111111101 &
b1101 "
b11110001 $
b1101 (
b11010 ,
b101 )
b11110001 +
b11110001 #
#1070000
b11111111111111111111111111111110 &
b1110 "
b11110110 $
b1110 (
b11100 ,
b11110110 )
b0 *
b11110110 +
b11110110 #
#1075000
b11111111111111111111111111111111 &
b1111 "
b11111011 $
b1111 (
b11110 ,
b11111011 )
b11111011 +
b11111011 #
#1080000
b0 &
b0 "
b0 $
b0 (
b0 ,
b0 )
b0 +
b0 #
#1085000
b1 &
b1 "
b101 $
b1 (
b10 ,
b101 )
b101 +
b101 #
#1090000
b10 &
b10 "
b1010 $
b10 (
b100 ,
b11110110 )
b10100 *
b1010 +
b1010 #
#1095000
b11 &
b11 "
b1111 $
b11 (
b110 ,
b11111011 )
b1111 +
b1111 #
#1100000
b100 &
b100 "
b10100 $
b100 (
b1000 ,
b0 )
b10100 +
b10100 #
#1105000
b101 &
b101 "
b11001 $
b101 (
b1010 ,
b101 )
b11001 +
b11001 #
#1110000
b110 &
b110 "
b11110 $
b110 (
b1100 ,
b11110110 )
b101000 *
b11110 +
b11110 #
#1115000
b111 &
b111 "
b100011 $
b111 (
b1110 ,
b11111011 )
b100011 +
b100011 #
#1120000
b1000 &
b110 %
b11111111111111111111111111111000 &
b110 !
b1000 "
b11010000 $
b1000 (
b110 '
b10000 ,
b0 )
b11010000 *
b11010000 +
b11010000 #
#1125000
b11111111111111111111111111111001 &
b1001 "
b11010110 $
b1001 (
b10010 ,
b110 )
b11010110 +
b11010110 #
#1130000
b11111111111111111111111111111010 &
b1010 "
b11011100 $
b1010 (
b10100 ,
b11110100 )
b11101000 *
b11011100 +
b11011100 #
#1135000
b11111111111111111111111111111011 &
b1011 "
b11100010 $
b1011 (
b10110 ,
b11111010 )
b11100010 +
b11100010 #
#1140000
b11111111111111111111111111111100 &
b1100 "
b11101000 $
b1100 (
b11000 ,
b0 )
b11101000 +
b11101000 #
